setup.cfg
setup.py
logging_unterpolation/__init__.py
logging_unterpolation.egg-info/PKG-INFO
logging_unterpolation.egg-info/SOURCES.txt
logging_unterpolation.egg-info/dependency_links.txt
logging_unterpolation.egg-info/top_level.txt
logging_unterpolation/tests/__init__.py
logging_unterpolation/tests/performance_results.py
logging_unterpolation/tests/test_unterpolation.py