Metadata-Version: 1.0
Name: logging-unterpolation
Version: 0.2.0
Summary: patch logging module to accept PEP-3101 formatting syntax
Home-page: https://bitbucket.org/rdennis463/logging_unterpolation
Author: Rob Dennis
Author-email: rdennis+unterpolation@gmail.com
License: UNKNOWN
Platform: UNKNOWN
Classifier: License :: OSI Approved :: MIT License
Classifier: Programming Language :: Python
Classifier: Programming Language :: Python :: 2
Classifier: Programming Language :: Python :: 2.6
Classifier: Programming Language :: Python :: 2.7
Classifier: Programming Language :: Python :: 3
Classifier: Programming Language :: Python :: 3.0
Classifier: Programming Language :: Python :: 3.1
Classifier: Programming Language :: Python :: 3.2
Classifier: Operating System :: OS Independent
Classifier: Intended Audience :: Developers
Classifier: Topic :: Software Development :: Libraries :: Python Modules
Classifier: Topic :: System :: Logging
Classifier: Development Status :: 5 - Production/Stable
